simple_catalyst_center/__init__.py
simple_catalyst_center/rest_client/LICENSE
simple_catalyst_center/rest_client/README
simple_catalyst_center/rest_client/__init__.py
simple_catalyst_center/rest_client/api.py
simple_catalyst_center/rest_client/curlify.py
simple_catalyst_center/rest_client/decorators.py
simple_catalyst_center/rest_client/exceptions.py
simple_catalyst_center/rest_client/models.py
simple_catalyst_center/rest_client/request.py
simple_catalyst_center/rest_client/resource.py
simple_catalyst_center-0.3.2.dist-info/licenses/LICENSE
simple_catalyst_center-0.3.2.dist-info/METADATA
simple_catalyst_center-0.3.2.dist-info/WHEEL
simple_catalyst_center-0.3.2.dist-info/top_level.txt
simple_catalyst_center-0.3.2.dist-info/RECORD
