Metadata-Version: 2.4
Name: simple_catalyst_center
Version: 0.3.2
Summary: Simple REST-client for Cisco Catalyst Center
Home-page: https://github.com/jinjamator/simple_catalyst_center
Author: Wilhelm Putz
Author-email: wilhelm.putz@cancom.com
License: ASL V2
Classifier: License :: OSI Approved :: Apache Software License
Classifier: Programming Language :: Python :: 3.7
Classifier: Programming Language :: Python :: 3.8
Classifier: Topic :: System :: Installation/Setup
Classifier: Topic :: System :: Systems Administration
Classifier: Topic :: Utilities
Requires-Python: >=3.7
License-File: LICENSE
Dynamic: author
Dynamic: author-email
Dynamic: classifier
Dynamic: description
Dynamic: description-content-type
Dynamic: home-page
Dynamic: license
Dynamic: license-file
Dynamic: requires-python
Dynamic: summary
